fair_detect_group_a/__init__.py
fair_detect_group_a/setup.py
fair_detect_group_a-0.30.dist-info/LICENSE
fair_detect_group_a-0.30.dist-info/METADATA
fair_detect_group_a-0.30.dist-info/WHEEL
fair_detect_group_a-0.30.dist-info/top_level.txt
fair_detect_group_a-0.30.dist-info/RECORD
