Metadata-Version: 2.1
Name: fair-detect-group-a
Version: 0.30
Summary: FairDetect Group A IE MBD part time assignment for Python II class
Home-page: https://github.com/Callisthenes/ai-bias-detect
Author: Team_A_MBD_2022_MBD
Author-email: pedrovesteban@student.ie.edu
License: MIT
Platform: UNKNOWN
License-File: LICENSE
